setup.py
demo/test.py
mongosion/__init__.py
mongosion.egg-info/PKG-INFO
mongosion.egg-info/SOURCES.txt
mongosion.egg-info/dependency_links.txt
mongosion.egg-info/top_level.txt