Metadata-Version: 1.0
Name: mongosion
Version: 0.1.3
Summary: A session moudel for tornado using mongodb
Home-page: https://github.com/grasses/mongosion
Author: xiaocao
Author-email: xiaocao.grasses@gmail.com
License: GPL
Keywords: mongodb,tornado,mongosion
Platform: UNKNOWN
